df_analyze/__init__.py
df_analyze/__main__.py
df_analyze/_constants.py
df_analyze/_main.py
df_analyze/_setup.py
df_analyze/_types.py
df_analyze/enumerables.py
df_analyze/feature_selection.py
df_analyze/hypertune.py
df_analyze/loading.py
df_analyze/nonsense.py
df_analyze/saving.py
df_analyze/scoring.py
df_analyze/timing.py
df_analyze/utils.py
df_analyze/analysis/calibration.py
df_analyze/analysis/metrics.py
df_analyze/analysis/univariate/associate.py
df_analyze/analysis/univariate/describe.py
df_analyze/analysis/univariate/predict/models.py
df_analyze/analysis/univariate/predict/predict.py
df_analyze/cli/arguments.py
df_analyze/cli/cli.py
df_analyze/cli/parsing.py
df_analyze/cli/text.py
df_analyze/legacy/src/classifiers.py
df_analyze/legacy/src/cleaning.py
df_analyze/legacy/src/objectives.py
df_analyze/legacy/src/regressors.py
df_analyze/models/base.py
df_analyze/models/dummy.py
df_analyze/models/knn.py
df_analyze/models/lgbm.py
df_analyze/models/linear.py
df_analyze/models/mlp.py
df_analyze/models/svm.py
df_analyze/preprocessing/cleaning.py
df_analyze/preprocessing/prepare.py
df_analyze/preprocessing/inspection/containers.py
df_analyze/preprocessing/inspection/inference.py
df_analyze/preprocessing/inspection/inspection.py
df_analyze/preprocessing/inspection/text.py
df_analyze/selection/embedded.py
df_analyze/selection/filter.py
df_analyze/selection/models.py
df_analyze/selection/stepwise.py
df_analyze/selection/wrapper.py
df_analyze/sklearn_pasta/_sequential.py
df_analyze/sklearn_pasta/_tags.py
df_analyze/testing/datasets.py
df_analyze-0.1.3.dist-info/METADATA
df_analyze-0.1.3.dist-info/WHEEL
df_analyze-0.1.3.dist-info/entry_points.txt
df_analyze-0.1.3.dist-info/RECORD
