Metadata-Version: 2.3
Name: df-analyze
Version: 0.1.3
Summary: Add your description here
Author: Derek Berger
Requires-Python: >=3.9
Requires-Dist: joblib>=1.4.2
Requires-Dist: jsonpickle>=3.0.4
Requires-Dist: lightgbm>=4.3.0
Requires-Dist: matplotlib>=3.9.0
Requires-Dist: numpy>=1.26.3
Requires-Dist: openml>=0.14.2
Requires-Dist: openpyxl>=3.1.2
Requires-Dist: optuna>=3.6.1
Requires-Dist: pandas>=2.2.2
Requires-Dist: pytest>=8.2.1
Requires-Dist: scikit-learn>=1.4.2
Requires-Dist: scipy>=1.13.0
Requires-Dist: skorch>=0.15.0
Requires-Dist: tabulate>=0.9.0
Requires-Dist: torch>=2.3.0
Requires-Dist: torchvision>=0.18.0
Requires-Dist: tqdm>=4.64.1
Requires-Dist: typing-extensions>=4.9.0
